examples
flask_xadmin
